experiencecloudapis/__init__.py
experiencecloudapis/analytics.py
experiencecloudapis/analytics_reports.py
experiencecloudapis/exceptions.py
experiencecloudapis/target.py
experiencecloudapis/utils.py
experiencecloudapis/authentication/__init__.py
experiencecloudapis/authentication/auth.py
experiencecloudapis/authentication/exceptions.py
experiencecloudapis/authentication/jwt.py
tests/__init__.py
tests/test_analytics.py
tests/test_analytics_reports.py
tests/test_exceptions.py
tests/test_jwt.py
tests/test_target.py
tests/test_utils.py
experiencecloudapis-1.2.0.dist-info/LICENSE.md
experiencecloudapis-1.2.0.dist-info/METADATA
experiencecloudapis-1.2.0.dist-info/WHEEL
experiencecloudapis-1.2.0.dist-info/top_level.txt
experiencecloudapis-1.2.0.dist-info/RECORD
