Metadata-Version: 2.1
Name: experiencecloudapis
Version: 1.2.0
Summary: Adobe Experience Cloud APIs Implementation for Python
Home-page: UNKNOWN
Author: DHL Web Analytics
Author-email: analytics@dpdhl.com
License: MIT
Platform: UNKNOWN
Requires-Python: >=3.6
Requires-Dist: requests
Requires-Dist: pandas
Requires-Dist: PyJWT
Requires-Dist: cryptography
